digautoprofiler/__init__.py
digautoprofiler/_version.py
digautoprofiler/profile_lib.py
digautoprofiler/utils.py
digautoprofiler/labextension/build_log.json
digautoprofiler/labextension/package.json
digautoprofiler/labextension/static/23eddca8640abf64e041.svg
digautoprofiler/labextension/static/lib_index_js.d9be532de14d1fdd7057.js
digautoprofiler/labextension/static/lib_index_js.d9be532de14d1fdd7057.js.map
digautoprofiler/labextension/static/remoteEntry.1be9ef3cb817003c3043.js
digautoprofiler/labextension/static/remoteEntry.1be9ef3cb817003c3043.js.map
digautoprofiler/labextension/static/style.js
digautoprofiler/labextension/static/style_index_js.2207dcdc3d3f4e9a3299.js
digautoprofiler/labextension/static/style_index_js.2207dcdc3d3f4e9a3299.js.map
digautoprofiler-3.0.1.data/data/share/jupyter/labextensions/digautoprofiler/build_log.json
digautoprofiler-3.0.1.data/data/share/jupyter/labextensions/digautoprofiler/install.json
digautoprofiler-3.0.1.data/data/share/jupyter/labextensions/digautoprofiler/package.json
digautoprofiler-3.0.1.data/data/share/jupyter/labextensions/digautoprofiler/static/23eddca8640abf64e041.svg
digautoprofiler-3.0.1.data/data/share/jupyter/labextensions/digautoprofiler/static/lib_index_js.d9be532de14d1fdd7057.js
digautoprofiler-3.0.1.data/data/share/jupyter/labextensions/digautoprofiler/static/lib_index_js.d9be532de14d1fdd7057.js.map
digautoprofiler-3.0.1.data/data/share/jupyter/labextensions/digautoprofiler/static/remoteEntry.1be9ef3cb817003c3043.js
digautoprofiler-3.0.1.data/data/share/jupyter/labextensions/digautoprofiler/static/remoteEntry.1be9ef3cb817003c3043.js.map
digautoprofiler-3.0.1.data/data/share/jupyter/labextensions/digautoprofiler/static/style.js
digautoprofiler-3.0.1.data/data/share/jupyter/labextensions/digautoprofiler/static/style_index_js.2207dcdc3d3f4e9a3299.js
digautoprofiler-3.0.1.data/data/share/jupyter/labextensions/digautoprofiler/static/style_index_js.2207dcdc3d3f4e9a3299.js.map
digautoprofiler-3.0.1.dist-info/LICENSE
digautoprofiler-3.0.1.dist-info/METADATA
digautoprofiler-3.0.1.dist-info/WHEEL
digautoprofiler-3.0.1.dist-info/top_level.txt
digautoprofiler-3.0.1.dist-info/RECORD
